imagedisplay/__init__.py
imagedisplay/__main__.py
imagedisplay-1.0.2.dist-info/METADATA
imagedisplay-1.0.2.dist-info/WHEEL
imagedisplay-1.0.2.dist-info/entry_points.txt
imagedisplay-1.0.2.dist-info/top_level.txt
imagedisplay-1.0.2.dist-info/RECORD
