Metadata-Version: 2.1
Name: imagedisplay
Version: 1.0.2
Summary: Display image
Home-page: https://github.com/ShashankVBhat/DisplayImage
Author: shashank
Author-email: bhatshashank8@gmail.com
License: UNKNOWN
Platform: UNKNOWN
Classifier: Programming Language :: Python
Classifier: Programming Language :: Python :: 2
Classifier: Programming Language :: Python :: 3
Requires-Dist: opencv-python
